gwss/__init__.py
gwss/cli.py
gwss/config.py
gwss/download.py
gwss/gwss.py
gwss/logger.py
gwss/resolver.py
gwss/resolver_config.py
gwss/unpkg.py
gwss/utilities.py
gwss/versions.py
gwss/__pycache__/__init__.cpython-311.pyc
gwss/__pycache__/cli.cpython-311.pyc
gwss/__pycache__/config.cpython-311.pyc
gwss/__pycache__/download.cpython-311.pyc
gwss/__pycache__/gwss.cpython-311.pyc
gwss/__pycache__/logger.cpython-311.pyc
gwss/__pycache__/resolver.cpython-311.pyc
gwss/__pycache__/resolver_config.cpython-311.pyc
gwss/__pycache__/unpkg.cpython-311.pyc
gwss/__pycache__/utilities.cpython-311.pyc
gwss/__pycache__/versions.cpython-311.pyc
gwss-0.0.6.data/scripts/gwss
gwss-0.0.6.dist-info/METADATA
gwss-0.0.6.dist-info/WHEEL
gwss-0.0.6.dist-info/top_level.txt
gwss-0.0.6.dist-info/RECORD
