Metadata-Version: 2.1
Name: gwss
Version: 0.0.6
Summary: get needed web scripts and styles
Home-page: 
Author: Ken Spencer / IotaSpencer
Author-email: IotaSpencer / Ken Spencer <me@iotaspencer.me>
License: MIT License
Project-URL: Homepage, https://github.com/IotaSpencer/gwss
Project-URL: Issues, https://github.com/IotaSpencer/gwss/issues
Classifier: Programming Language :: Python :: 3
Classifier: License :: OSI Approved :: MIT License
Classifier: Operating System :: OS Independent
Classifier: Development Status :: 4 - Beta
Classifier: Environment :: Web Environment
Classifier: Intended Audience :: Developers
Classifier: License :: OSI Approved :: MIT License
Classifier: Programming Language :: Python :: 3.10
Classifier: Programming Language :: Python :: 3.11
Classifier: Programming Language :: Python :: 3.12
Classifier: Programming Language :: Python :: 3.13
Classifier: Topic :: Internet :: WWW/HTTP :: Site Management
Classifier: Typing :: Typed
Classifier: Topic :: System :: Software Distribution
Requires-Python: >=3.10
Requires-Dist: lastversion ~=3.4.6
Requires-Dist: aiohttp ~=3.9.2
Requires-Dist: click ~=8.1.7
Requires-Dist: colorlog ~=6.8.2
Requires-Dist: pytest ~=8.0.0
Requires-Dist: setuptools ~=59.6.0
Requires-Dist: PyYAML ~=6.0.1
Requires-Dist: jinja2 ~=3.1.3
Requires-Dist: colorama ~=0.4.6
Requires-Dist: furl ~=2.1.3
Requires-Dist: requests ~=2.31.0
Requires-Dist: download ~=0.3.5
